Workbook

Sheet Uruguay P&L
B2: URUGUAY
B4: '000 USD | D4: Q2RF | F4: Q1RF | G4: vs Q1RF | H4: vs Q1RF % | I4: 24PF | J4: vs 24PF | K4: vs 24PF %
B7: Net Sales | D7: 721 | F7: 644 | G7: =D7-F7 -> 77 | H7: =IFERROR(G7/F7,0) -> 0.11956522 | I7: 569 | J7: =D7-I7 -> 152 | K7: =IFERROR(J7/I7,0) -> 0.26713533
B9: SFLICTOS | D9: 329 | F9: 294 | G9: =-D9+F9 -> -35 | H9: =IFERROR(G9/F9,0) -> -0.11904762 | I9: 287 | J9: =-D9+I9 -> -42 | K9: =IFERROR(J9/I9,0) -> -0.14634146
B10: % ratio | D10: =IFERROR(D9/D$7,0) -> 0.45631068 | F10: =IFERROR(F9/F$7,0) -> 0.45652174 | G10: =ROUND((-D10+F10)*100,1)&" p.p." -> 0 p.p. | I10: 0.505 | J10: =ROUND((-D10+I10)*100,1)&" p.p." -> 4,9 p.p.
B11: Severance | F11: 0 | G11: =-D11+F11 -> 0 | H11: =IFERROR(G11/F11,0) -> 0 | I11: -15 | J11: =-D11+I11 -> -15 | K11: =IFERROR(J11/I11,0) -> 1
B12: Other Staff Costs | D12: 69 | F12: 62 | G12: =-D12+F12 -> -7 | H12: =IFERROR(G12/F12,0) -> -0.11290323 | I12: 49 | J12: =-D12+I12 -> -20 | K12: =IFERROR(J12/I12,0) -> -0.40816327
B14: Staff Costs | D14: =SUM(D9,D11:D12) -> 398 | F14: =SUM(F9,F11:F12) -> 356 | G14: =-D14+F14 -> -42 | H14: =IFERROR(G14/F14,0) -> -0.11797753 | I14: 320 | J14: =-D14+I14 -> -78 | K14: =IFERROR(J14/I14,0) -> -0.24375
B15: % ratio | D15: =IFERROR(D14/D$7,0) -> 0.5520111 | F15: =IFERROR(F14/F$7,0) -> 0.55279503 | G15: =ROUND((-D15+F15)*100,1)&" p.p." -> 0,1 p.p. | I15: 0.563 | J15: =ROUND((-D15+I15)*100,1)&" p.p." -> 1,1 p.p.
B17: Establishment Costs | D17: 32.4 | F17: 32 | G17: =-D17+F17 -> -0.4 | H17: =IFERROR(G17/F17,0) -> -0.0125 | I17: 29 | J17: =-D17+I17 -> -3.4 | K17: =IFERROR(J17/I17,0) -> -0.11724138
B18: % ratio | D18: =IFERROR(D17/D$7,0) -> 0.044937587 | F18: =IFERROR(F17/F$7,0) -> 0.049689441 | G18: =ROUND((-D18+F18)*100,1)&" p.p." -> 0,5 p.p. | I18: =IFERROR(I17/I$7,0) -> 0.050966608 | J18: =ROUND((-D18+I18)*100,1)&" p.p." -> 0,6 p.p.
B20: Personal Costs | D20: 11.49 | F20: 9 | G20: =-D20+F20 -> -2.49 | H20: =IFERROR(G20/F20,0) -> -0.27666667 | I20: 4 | J20: =-D20+I20 -> -7.49 | K20: =IFERROR(J20/I20,0) -> -1.8725
B21: Overhead | D21: 68 | F21: 68 | G21: =-D21+F21 -> 0 | H21: =IFERROR(G21/F21,0) -> 0 | I21: 60 | J21: =-D21+I21 -> -8 | K21: =IFERROR(J21/I21,0) -> -0.13333333
B22: Other G&A Costs | D22: 60 | F22: 48 | G22: =-D22+F22 -> -12 | H22: =IFERROR(G22/F22,0) -> -0.25 | I22: 46 | J22: =-D22+I22 -> -14 | K22: =IFERROR(J22/I22,0) -> -0.30434783
B23: G&A Costs | D23: =SUM(D20:D22) -> 139.49 | F23: =SUM(F20:F22) -> 125 | G23: =SUM(G20:G22) -> -14.49 | H23: =IFERROR(G23/F23,0) -> -0.11592 | I23: 109 | J23: =SUM(J20:J22) -> -29.49 | K23: =IFERROR(J23/I23,0) -> -0.27055046
B24: % ratio | D24: =IFERROR(D23/D$7,0) -> 0.19346741 | F24: =IFERROR(F23/F$7,0) -> 0.19409938 | G24: =ROUND((-D24+F24)*100,1)&" p.p." -> 0,1 p.p. | I24: =IFERROR(I23/I$7,0) -> 0.19156415 | J24: =ROUND((-D24+I24)*100,1)&" p.p." -> -0,2 p.p.
B26: Operating Profit | D26: =SUM(D7,-D14,-D17,-D23) -> 151.11 | F26: =SUM(F7,-F14,-F17,-F23) -> 131 | G26: =SUM(G7,G14,G17,G23) -> 20.11 | H26: =IFERROR(G26/F26,0) -> 0.15351145 | I26: 109 | J26: =SUM(J7,J14,J17,J23) -> 41.11 | K26: =IFERROR(J26/I26,0) -> 0.37715596
B27: % margin | D27: =IFERROR(D26/D$7,0) -> 0.20958391 | F27: =IFERROR(F26/F$7,0) -> 0.20341615 | G27: =ROUND((D27-F27)*100,1)&" p.p." -> 0,6 p.p. | I27: =IFERROR(I26/I$7,0) -> 0.19156415 | J27: =ROUND((D27-I27)*100,1)&" p.p." -> 1,8 p.p.
B29: HC - Period End | D29: 11 | F29: 8 | G29: =-D29+F29 -> -3 | H29: =IFERROR(G29/F29,0) -> -0.375 | I29: 8 | J29: =-D29+I29 -> -3 | K29: =IFERROR(J29/I29,0) -> -0.375
B31: New Business | D31: 39 | F31: 64 | G31: =-D31+F31 -> 25 | H31: =IFERROR(G31/F31,0) -> 0.390625
B32: % of Rem. Net Sales | D32: =D31/D7 -> 0.05409154 | F32: =F31/F7 -> 0.099378882 | G32: =ROUND((-D32+F32)*100,1)&" p.p." -> 4,5 p.p.
B34: Total Pipeline | D34: =Pipeline!H7/1000 -> 136.8
B35: % of New Business | D35: =IFERROR(D34/D$31,0) -> 3.5076923
B37: Pipeline Weighted | D37: =Pipeline!K7/1000 -> 48.64
B38: % of New Business | D38: =IFERROR(D37/D$31,0) -> 1.2471795
B42: Attrition
B43: Annual savings: | F43: 0 | G43: =-F43+D43 -> 0 | H43: =-IFERROR(G43/F43,0) -> 0
B44: Headcount impact: | F44: 0 | G44: =-F44+D44 -> 0 | H44: =-IFERROR(G44/F44,0) -> 0

Sheet Uruguay Phasing
B2: URUGUAY
O3: '000 USD
C4: JANUARY | D4: FEBRUARY | E4: MARCH | F4: APRIL | G4: MAY | H4: JUNE | I4: JULY | J4: AUGUST | K4: SEPTEMBER | L4: OCTOBER | M4: NOVEMBER | N4: DECEMBER | O4: 2025 TOTAL
B7: 2025 Q1RF
B8: Net Sales | C8: 49 | D8: 55 | E8: 41 | F8: 62 | G8: 53 | H8: 78 | I8: 62 | J8: 69 | K8: 64 | L8: 68 | M8: 64 | N8: 67 | O8: =SUM(C8:N8) -> 732 | P8: ='Uruguay P&L'!D7 -> 721
B9: Staff Costs | C9: 30.392407 | D9: 24.708449 | E9: 27.813125 | F9: 28.158727 | G9: 29.685278 | H9: 34.190255 | I9: 36.960579 | J9: 36.960579 | K9: 36.960579 | L9: 36.960579 | M9: 36.960579 | N9: 36.960579 | O9: =SUM(C9:N9) -> 396.71171 | P9: ='Uruguay P&L'!D14 -> 398
B10: Operating Profit | C10: -4.3018287 | D10: 46.465185 | E10: 12.19963 | F10: 13.215532 | G10: 7.3395602 | H10: 16.029769 | I10: -8.0322917 | J10: 8.6925231 | K10: 1.1390972 | L10: 8.1260648 | M10: 2.9184491 | N10: 26.78375 | O10: =SUM(C10:N10) -> 130.57544 | P10: ='Uruguay P&L'!D26 -> 151.11
B11: % margin | C11: =IFERROR(C10/C8,0) -> -0.087792423 | D11: =IFERROR(D10/D8,0) -> 0.84482155 | E11: =IFERROR(E10/E8,0) -> 0.29755194 | F11: =IFERROR(F10/F8,0) -> 0.21315375 | G11: =IFERROR(G10/G8,0) -> 0.13848227 | H11: =IFERROR(H10/H8,0) -> 0.20550985 | I11: =IFERROR(I10/I8,0) -> -0.12955309 | J11: =IFERROR(J10/J8,0) -> 0.1259786 | ... O11: =IFERROR(O10/O8,0) -> 0.17838175
B13: Net Sales | C13: =IFERROR(SUM(C8:E8)/$O8,0) -> 0.19808743 | F13: =IFERROR(SUM(F8:H8)/$O8,0) -> 0.2636612 | I13: =IFERROR(SUM(I8:K8)/$O8,0) -> 0.26639344 | L13: =IFERROR(SUM(L8:N8)/$O8,0) -> 0.27185792
B14: Staff Costs | C14: =IFERROR(SUM(C9:E9)/$O9,0) -> 0.20900311 | F14: =IFERROR(SUM(F9:H9)/$O9,0) -> 0.2319928 | I14: =IFERROR(SUM(I9:K9)/$O9,0) -> 0.27950205 | L14: =IFERROR(SUM(L9:N9)/$O9,0) -> 0.27950205
B15: Operating Profit | C15: =IFERROR(SUM(C10:E10)/$O10,0) -> 0.41633393 | F15: =IFERROR(SUM(F10:H10)/$O10,0) -> 0.2801818 | I15: =IFERROR(SUM(I10:K10)/$O10,0) -> 0.013779993 | L15: =IFERROR(SUM(L10:N10)/$O10,0) -> 0.28970428
O16: variations between +1% and -1% over 2024
B20: 2024 PF
B21: Net Sales | C21: 45 | D21: 47 | E21: 41 | F21: 56 | G21: 58 | H21: 45 | I21: 43 | J21: 45 | K21: 35 | L21: 59 | M21: 43 | N21: 50 | O21: 569
B22: Staff Costs | C22: 31 | D22: 30 | E22: 31 | F22: 13 | G22: 27 | H22: 25 | I22: 27 | J22: 29 | K22: 24 | L22: 28 | M22: 28 | N22: 27 | O22: =SUM(C22:N22) -> 320
B23: Operating Profit | C23: 1 | D23: 10 | E23: -16 | F23: 26 | G23: 43 | H23: 12 | I23: 5 | J23: 4 | K23: 7 | L23: 23 | M23: 4 | N23: -10 | O23: =SUM(C23:N23) -> 109
B24: % margin | C24: =IFERROR(C23/C21,0) -> 0.022222222 | D24: =IFERROR(D23/D21,0) -> 0.21276596 | E24: =IFERROR(E23/E21,0) -> -0.3902439 | F24: =IFERROR(F23/F21,0) -> 0.46428571 | G24: =IFERROR(G23/G21,0) -> 0.74137931 | H24: =IFERROR(H23/H21,0) -> 0.26666667 | I24: =IFERROR(I23/I21,0) -> 0.11627907 | J24: =IFERROR(J23/J21,0) -> 0.088888889 | ... O24: =IFERROR(O23/O21,0) -> 0.19156415
B26: Net Sales | C26: =IFERROR(SUM(C21:E21)/SUM(C21:N21),0) -> 0.2345679 | F26: =IFERROR(SUM(F21:H21)/SUM(C21:N21),0) -> 0.28042328 | I26: =IFERROR(SUM(I21:K21)/SUM(C21:N21),0) -> 0.21693122 | L26: =IFERROR(SUM(L21:N21)/SUM(C21:N21),0) -> 0.2680776
B27: Staff Costs | C27: =IFERROR(SUM(C22:E22)/SUM(C22:N22),0) -> 0.2875 | F27: =IFERROR(SUM(F22:H22)/SUM(C22:N22),0) -> 0.203125 | I27: =IFERROR(SUM(I22:K22)/SUM(C22:N22),0) -> 0.25 | L27: =IFERROR(SUM(L22:N22)/SUM(C22:N22),0) -> 0.259375
B28: Operating Profit | C28: =IFERROR(SUM(C23:E23)/SUM(C23:N23),0) -> -0.04587156 | F28: =IFERROR(SUM(F23:H23)/SUM(C23:N23),0) -> 0.74311927 | I28: =IFERROR(SUM(I23:K23)/SUM(C23:N23),0) -> 0.14678899 | L28: =IFERROR(SUM(L23:N23)/SUM(C23:N23),0) -> 0.1559633

Sheet Pipeline
B2: PIPELINE
B4: Country | C4: Brand | D4: Client/Prospect | E4: Project Name | F4: Type | G4: Probability | H4: Annual Fee | I4: 2025 Impact | J4: Annual Fee (Weighted) | K4: 2025 Impact (Weighted)
G5: % | H5: '000 USD | I5: '000 USD | J5: '000 USD | K5: '000 USD
H7: =SUM(H$10:H$500) -> 136800 | I7: =SUM(I$10:I$500) -> 60800 | J7: =SUM(J$10:J$500) -> 109440 | K7: =SUM(K$10:K$500) -> 48640
B10: Uruguay | C10: Burson | D10: schenck | G10: 0.8 | H10: 8000 | I10: 8000 | J10: =$G$10*H10 -> 6400 | K10: =$G$10*I10 -> 6400
D11: dlocal | G11: 0.3 | H11: 2500 | I11: 2500 | J11: =$G$10*H11 -> 2000 | K11: =$G$10*I11 -> 2000
D12: Pag Brasil | G12: 0.2 | H12: 32000 | I12: 10000 | J12: =$G$10*H12 -> 25600 | K12: =$G$10*I12 -> 8000
D13: BSE | G13: 0.9 | H13: 1300 | I13: 1300 | J13: =$G$10*H13 -> 1040 | K13: =$G$10*I13 -> 1040
D14: UPM | G14: 0.6 | H14: 3000 | I14: 3000 | J14: =$G$10*H14 -> 2400 | K14: =$G$10*I14 -> 2400
D15: EQUEIFAX | G15: 0.6 | H15: 2000 | I15: 2000 | J15: =$G$10*H15 -> 1600 | K15: =$G$10*I15 -> 1600
D16: EPSON | G16: 0.6 | H16: 60000 | I16: 20000 | J16: =$G$10*H16 -> 48000 | K16: =$G$10*I16 -> 16000
D17: Mc Kinsey | G17: 0.25 | H17: 18000 | I17: 9000 | J17: =$G$10*H17 -> 14400 | K17: =$G$10*I17 -> 7200
D18: Interfase | G18: 0.3 | H18: 10000 | I18: 5000 | J18: =$G$10*H18 -> 8000 | K18: =$G$10*I18 -> 4000
J19: =$G$10*H19 -> 0 | K19: =$G$10*I19 -> 0
J20: =$G$10*H20 -> 0 | K20: =$G$10*I20 -> 0
J21: =$G$10*H21 -> 0 | K21: =$G$10*I21 -> 0
J22: =$G$10*H22 -> 0 | K22: =$G$10*I22 -> 0
J23: =$G$10*H23 -> 0 | K23: =$G$10*I23 -> 0
J24: =$G$10*H24 -> 0 | K24: =$G$10*I24 -> 0
J25: =$G$10*H25 -> 0 | K25: =$G$10*I25 -> 0
J26: =$G$10*H26 -> 0 | K26: =$G$10*I26 -> 0
J27: =$G$10*H27 -> 0 | K27: =$G$10*I27 -> 0
J28: =$G$10*H28 -> 0 | K28: =$G$10*I28 -> 0
J29: =$G$10*H29 -> 0 | K29: =$G$10*I29 -> 0
J30: =$G$10*H30 -> 0 | K30: =$G$10*I30 -> 0
... J236: =$G$10*H236 -> 0 | K236: =$G$10*I236 -> 0

Sheet Setup
A1: Country | B1: Brand | C1: Type
A2: Argentina | B2: Burson | C2: New Client
A3: Brazil | B3: Jeffrey Group | C3: Organic - Renewal
A4: Chile | B4: Maquina | C4: Organic - Project
A5: Colombia
A6: Mexico
A7: Miami
A8: Peru
A9: Puerto Rico
A10: Uruguay
